[
  {
    "Time": "36:50",
    "Place": 1,
    "Seconds": 2210,
    "Name": "Marco Pantani",
    "Year": 1995,
    "Nationality": "ITA",
    "Doping": "Alleged drug use during 1995 due to high hematocrit levels",
    "URL": "https://en.wikipedia.org/wiki/Marco_Pantani#Alleged_drug_use"
  },
  {
    "Time": "36:55",
    "Place": 2,
    "Seconds": 2215,
    "Name": "Marco Pantani",
    "Year": 1997,
    "Nationality": "ITA",
    "Doping": "Alleged drug use during 1997 due to high hermatocrit levels",
    "URL": "https://en.wikipedia.org/wiki/Marco_Pantani#Alleged_drug_use"
  }
]